signal_processor/__init__.py
signal_processor/processor.py
pw_signal_processor-0.1.3.dist-info/METADATA
pw_signal_processor-0.1.3.dist-info/WHEEL
pw_signal_processor-0.1.3.dist-info/top_level.txt
pw_signal_processor-0.1.3.dist-info/RECORD
