Metadata-Version: 2.1
Name: pw-signal-processor
Version: 0.1.3
Summary: A lightweight Python library offering moving average, first-order low-pass filtering, FFT, and STFT analysis.
Home-page: https://github.com/pinklab-art/signal_processor
Author: PinkWink
Author-email: pinkwink@pinklab.art
License: MIT
Classifier: Programming Language :: Python :: 3
Classifier: License :: OSI Approved :: MIT License
Classifier: Operating System :: OS Independent
Requires-Python: >=3.6
Requires-Dist: numpy>=1.16.0
Requires-Dist: matplotlib>=3.0.0
Requires-Dist: scipy>=1.2.0
